mb_drf_extensions/__init__.py
mb_drf_extensions/authentication.py
mb_drf_extensions/exceptions.py
mb_drf_extensions/filters.py
mb_drf_extensions/mixins.py
mb_drf_extensions/mocks.py
mb_drf_extensions/pagination.py
mb_drf_extensions/permissions.py
mb_drf_extensions/response.py
mb_drf_extensions/settings.py
mb_drf_extensions/views.py
mb_drf_extensions/viewsets.py
mb_drf_extensions-0.1.0.dist-info/LICENSE
mb_drf_extensions-0.1.0.dist-info/METADATA
mb_drf_extensions-0.1.0.dist-info/WHEEL
mb_drf_extensions-0.1.0.dist-info/top_level.txt
mb_drf_extensions-0.1.0.dist-info/RECORD
